main.py
bytekafka-98.7.dist-info/METADATA
bytekafka-98.7.dist-info/WHEEL
bytekafka-98.7.dist-info/top_level.txt
bytekafka-98.7.dist-info/RECORD
